wisdomweaver/__init__.py
wisdomweaver/__main__.py
wisdomweaver/database.py
wisdomweaver/document.py
wisdomweaver/models.py
wisdomweaver/postprocessor.py
wisdomweaver-0.4.0.dist-info/LICENSE
wisdomweaver-0.4.0.dist-info/METADATA
wisdomweaver-0.4.0.dist-info/WHEEL
wisdomweaver-0.4.0.dist-info/entry_points.txt
wisdomweaver-0.4.0.dist-info/top_level.txt
wisdomweaver-0.4.0.dist-info/RECORD
