Metadata-Version: 2.1
Name: wisdomweaver
Version: 0.4.0
Summary: Wisdom indexer and generator
Author-email: Martin Schröder <info@swedishembedded.com>
License: Copyright (C) 2023 Martin Schröder <info@swedishembedded.com>
Project-URL: Homepage, https://github.com/swedishembedded/wisdomweaver
Keywords: llm,languagemodel,indexing
Classifier: License :: OSI Approved :: Apache Software License
Classifier: Programming Language :: Python
Classifier: Programming Language :: Python :: 3
Requires-Python: >=3.9
License-File: LICENSE
Requires-Dist: torch
Requires-Dist: pypdf
Requires-Dist: nltk
Requires-Dist: sentence-transformers
Requires-Dist: qdrant-client
Requires-Dist: openai
Requires-Dist: guidance
Requires-Dist: xformers
Provides-Extra: dev
Requires-Dist: black ; extra == 'dev'
Requires-Dist: bumpversion ; extra == 'dev'
Requires-Dist: isort ; extra == 'dev'
Requires-Dist: pip-tools ; extra == 'dev'
Requires-Dist: pytest ; extra == 'dev'
